{"url":"https://www.strebenacademy.com/becas/","title":"Becas | STREBEN ACADEMY","description":"¡Tenemos una beca para ti! Creemos que el talento y el compromiso merecen ser impulsados. Por ello, contamos con un programa de becas diseñado para reconocer el esfuerzo y facilitar el acceso a una formación de calidad. ¡Solicita tu beca al final de la página!","canonical":null,"h1":["¡Tenemos una beca para ti!"],"h2":["¡Importante!"],"h3":["Beca por aprovechamiento","Beca por familiares","Beca por recomendación","Beca Full Learning","Política de cookies"],"imgsMissingAlt":6,"imgsTotal":6,"becas":{"aprovechamiento":"15% (promedio ≥85/100)","familiares":"15% (2+ familiares)","recomendacion":"10% (referido no familiar)","full_learning":"15% (2+ cursos simultáneos)"},"contacto_email":"streben.academy@gmail.com","beca_form":"https://forms.gle/u7wChFhaMGxaecQ89","notas":["H1 único correcto","Description buena (con copy real)","Imgs sin alt: 6/6","H3 'Política de cookies' está siendo arrastrado del banner — heading rank confuso"]}
